result_viewer/ResultViewer.py
result_viewer/ResultsParser.py
result_viewer/__init__.py
result_viewer/main.py
result_viewer/ui.py
result_viewer/Plugins/ReportHTML.py
result_viewer/Plugins/__init__.py
result_viewer/Plugins/create_html.py
result_viewer/reporting/html_formatter.py
result_viewer/reporting/html_report.py
result_viewer-0.0.1.dist-info/LICENSE
result_viewer-0.0.1.dist-info/METADATA
result_viewer-0.0.1.dist-info/WHEEL
result_viewer-0.0.1.dist-info/entry_points.txt
result_viewer-0.0.1.dist-info/top_level.txt
result_viewer-0.0.1.dist-info/RECORD
